README.md
setup.cfg
setup.py
neural_net_drawer/__init__.py
neural_net_drawer/drawer.py
neural_net_drawer.egg-info/PKG-INFO
neural_net_drawer.egg-info/SOURCES.txt
neural_net_drawer.egg-info/dependency_links.txt
neural_net_drawer.egg-info/requires.txt
neural_net_drawer.egg-info/top_level.txt