Metadata-Version: 2.1
Name: neural_net_drawer
Version: 0.0.3
Summary: Plugin for visual display of a neural network.
Home-page: https://github.com/EvgeniBondarev/Neural-Network-Drawer.git
Author: EvgeniBondarev
Author-email: bondareff7@gmail.com
Project-URL: Documentation, https://github.com/EvgeniBondarev/Neural-Network-Drawer.git
Keywords: neural network display visual
Classifier: Programming Language :: Python :: 3.11
Classifier: License :: OSI Approved :: MIT License
Classifier: Operating System :: OS Independent
Requires-Python: >=3.7
Requires-Dist: matplotlib
